Metadata-Version: 2.1
Name: fw-py-core
Version: 0.0.1
Summary: Python core library'
Home-page: UNKNOWN
Author: rainmakers
Author-email: rainmakers9090@gmail.com
License: UNKNOWN
Platform: UNKNOWN
Classifier: Programming Language :: Python :: 3
Classifier: License :: OSI Approved :: MIT License
Classifier: Operating System :: OS Independent
